vigilia/__init__.py
vigilia/assemble_fragments.py
vigilia/conf.py
vigilia/extract_patches.py
vigilia/lib/__init__.py
vigilia/lib/agent.py
vigilia/lib/git.py
vigilia/lib/io.py
vigilia/lib/tokens.py
vigilia/lib/tree.py
vigilia/py.typed
vigilia/summarise_changes.py
vigilia/summarise_fragments.py
vigilia-2026.1.4.dev1.dist-info/WHEEL
vigilia-2026.1.4.dev1.dist-info/entry_points.txt
vigilia-2026.1.4.dev1.dist-info/METADATA
vigilia-2026.1.4.dev1.dist-info/RECORD
