Metadata-Version: 2.3
Name: vigilia
Version: 2026.1.4.dev1
Summary: A CLI tool for generating technical summaries of code changes using LLMs
Author: Alejandro Giacometti
Author-email: Alejandro Giacometti <alejandro.giacometti@beauhurst.com>
Requires-Dist: pydantic-ai>=1.40.0
Requires-Dist: pygit2>=1.19.1
Requires-Dist: rich>=14.2.0
Requires-Dist: rustworkx>=0.17.1
Requires-Dist: tiktoken>=0.12.0
Requires-Dist: typer>=0.21.1
Requires-Python: >=3.13
